zodchy_alchemy/__init__.py
zodchy_alchemy/adapters/__init__.py
zodchy_alchemy/adapters/cqea.py
zodchy_alchemy/assemblers/__init__.py
zodchy_alchemy/assemblers/filters.py
zodchy_alchemy/assemblers/joins.py
zodchy_alchemy/assemblers/mutations.py
zodchy_alchemy/assemblers/orders.py
zodchy_alchemy/assemblers/queries.py
zodchy_alchemy/assemblers/slices.py
zodchy_alchemy/contracts.py
zodchy_alchemy/serializers/__init__.py
zodchy_alchemy/serializers/row.py
zodchy_alchemy-0.2.1.dist-info/METADATA
zodchy_alchemy-0.2.1.dist-info/WHEEL
zodchy_alchemy-0.2.1.dist-info/RECORD
