Metadata-Version: 2.1
Name: zodchy-alchemy
Version: 0.2.1
Summary: SqlAlchemy query builder for Zodchy operators
Home-page: https://github.com/smairon/zodchy-alchemy
Author: Feofilaktov, Sergey
Author-email: man@smairon.ru
Requires-Python: >=3.11,<4.0
Classifier: Programming Language :: Python :: 3
Classifier: Programming Language :: Python :: 3.11
Classifier: Programming Language :: Python :: 3.12
Requires-Dist: sqlalchemy (>=2.0,<3.0)
Requires-Dist: zodchy (>=0,<1)
Project-URL: Repository, https://github.com/smairon/zodchy-alchemy
